pastit_cli/__init__.py
pastit_cli/config.py
pastit_cli/pasta.py
pastit_cli/pastit.py
pastit_cli/setup_cmd.py
pastit_cli-1.0.7.dist-info/METADATA
pastit_cli-1.0.7.dist-info/WHEEL
pastit_cli-1.0.7.dist-info/entry_points.txt
pastit_cli-1.0.7.dist-info/top_level.txt
pastit_cli-1.0.7.dist-info/RECORD
